alex_tools_dhawth/__init__.py
alex_tools_dhawth/alex_tools.py
alex_tools-0.1.4.dist-info/METADATA
alex_tools-0.1.4.dist-info/WHEEL
alex_tools-0.1.4.dist-info/top_level.txt
alex_tools-0.1.4.dist-info/RECORD
